README.md
setup.py
novels/__init__.py
novels/__main__.py
novels/novels.py
novels.egg-info/PKG-INFO
novels.egg-info/SOURCES.txt
novels.egg-info/dependency_links.txt
novels.egg-info/entry_points.txt
novels.egg-info/requires.txt
novels.egg-info/top_level.txt