Metadata-Version: 2.1
Name: novels
Version: 0.0.52
Summary: free novel retriever
Home-page: https://bitbucket.org/everwalker/free-novels/src/master/
Author: Yonghang Wang
Author-email: wyhang@gmail.com
License: Apache 2
Keywords: novel
Platform: UNKNOWN
Classifier: License :: OSI Approved :: Apache Software License
